agile_north_build_essentials.py
agile_north_build_essentials-0.0.8.dist-info/LICENSE.txt
agile_north_build_essentials-0.0.8.dist-info/METADATA
agile_north_build_essentials-0.0.8.dist-info/WHEEL
agile_north_build_essentials-0.0.8.dist-info/top_level.txt
agile_north_build_essentials-0.0.8.dist-info/RECORD
